{"cameraMode":{"drawMode":0,"name":"Shaded","section":"Shading Mode"},"sceneLighting":true,"audioPlay":false,"sceneViewState":{"m_AlwaysRefresh":false,"showFog":true,"showSkybox":true,"showFlares":true,"showImageEffects":true,"showParticleSystems":true,"showVisualEffectGraphs":true,"m_FxEnabled":true},"in2DMode":false,"pivot":{"x":9.811771392822266,"y":0.7569313645362854,"z":-5.045074939727783},"rotation":{"x":-0.011745289899408818,"y":0.9820050597190857,"z":-0.06521208584308624,"w":-0.17686860263347627},"size":3.154492139816284,"orthographic":false}